mcp_server_sec_agent/__init__.py
mcp_server_sec_agent/config.py
mcp_server_sec_agent/const.py
mcp_server_sec_agent/server.py
mcp_server_sec_agent/client/__init__.py
mcp_server_sec_agent/client/model.py
mcp_server_sec_agent/client/model_test.py
mcp_server_sec_agent/client/sec_intelligent_client.py
sec_agent_mcp_server-0.1.2.dist-info/METADATA
sec_agent_mcp_server-0.1.2.dist-info/WHEEL
sec_agent_mcp_server-0.1.2.dist-info/entry_points.txt
sec_agent_mcp_server-0.1.2.dist-info/top_level.txt
sec_agent_mcp_server-0.1.2.dist-info/RECORD
