Metadata-Version: 2.4
Name: sec-agent-mcp-server
Version: 0.1.2
Summary: Add your description here
Requires-Python: >=3.13
Requires-Dist: mcp[cli]>=1.6.0
Requires-Dist: pip>=25.0.1
Requires-Dist: requests>=2.32.3
Requires-Dist: volcengine-python-sdk>=1.1.5
